asyncioget/README.MD
asyncioget/__init__.py
asyncioget/requirements.txt
asyncioget/thirdparty.json
asyncioget-0.11.dist-info/LICENSE.rst
asyncioget-0.11.dist-info/METADATA
asyncioget-0.11.dist-info/WHEEL
asyncioget-0.11.dist-info/top_level.txt
asyncioget-0.11.dist-info/RECORD
