Metadata-Version: 2.1
Name: asyncioget
Version: 0.11
Summary: simplifies the process of downloading multiple URLs concurrently, provides control over concurrency, and offers flexibility for customization
Home-page: https://github.com/hansalemaos/asyncioget
Author: Johannes Fischer
Author-email: aulasparticularesdealemaosp@gmail.com
License: MIT
Keywords: requests,asyncio
Classifier: Development Status :: 4 - Beta
Classifier: Programming Language :: Python :: 3 :: Only
Classifier: Programming Language :: Python :: 3.10
Classifier: Topic :: Software Development :: Libraries :: Python Modules
Classifier: Topic :: Utilities
License-File: LICENSE.rst
Requires-Dist: requests
